[
{"field" : "first_name:string:nullable", "type":"text", "validations": ""},
{"field" : "last_name:string:nullable", "type":"text", "validations": ""},
{"field" : "display_name:string:nullable", "type":"text", "validations": ""},
{"field" : "slug:string:nullable", "type": "text", "validations": ""},
{"field" : "position:string:nullable", "type":"text", "validations": ""},
{"field" : "supervisor:string:nullable", "type":"text", "validations": ""},
{"field" : "employment_title:string:nullable", "type":"text", "validations": ""},
{"field" : "employment_role:string:nullable", "type":"text", "validations": ""},
{"field" : "employment_status:string:nullable", "type":"select:Active Full-Time,ActivePart-time,OnContract,OnLeave,Terminated", "validations": ""},
{"field" : "phone:string:nullable", "type":"text", "validations": ""},
{"field" : "phone_type:string:nullable", "type":"select:Home,Mobile,Work,Other", "validations": ""},
{"field" : "website:string:nullable", "type":"text", "validations": ""},
{"field" : "company:string:nullable", "type":"text", "validations": ""},
{"field" : "gender:string:nullable", "type":"select:Male,Female", "validations": ""},
{"field" : "about_me:text", "type":"textarea", "validations": ""},
{"field" : "note:text", "type":"textarea", "validations": ""},
{"field" : "skypeid:string:nullable", "type": "text", "validations": ""},
{"field" : "twittername:string:nullable", "type":"text", "validations": ""},
{"field" : "linkedinurl:string:nullable", "type":"text", "validations": ""},
{"field" : "googleplusurl:string:nullable", "type":"text", "validations": ""},
{"field" : "facebookurl:string:nullable", "type":"text", "validations": ""},
{"field" : "user_api_key:string:nullable", "type":"text", "validations": ""},
{"field" : "user_api_secret:string:nullable", "type":"text", "validations": ""},
{"field" : "user_activation_key:string:nullable", "type":"text", "validations": ""},
{"field" : "activation_code_id:string:nullable", "type":"text", "validations": ""},
{"field" : "activation_code:string:nullable", "type":"text", "validations": ""},
{"field" : "confirmation_code:string:nullable", "type":"text", "validations": ""},
{"field" : "confirmed:boolean:default,0", "type":"checkbox", "validations": ""},
{"field" : "activated:boolean:default,0", "type":"checkbox", "validations": ""},
{"field" : "published:boolean:default,0", "type":"checkbox", "validations": ""},
{"field" : "last_login:timestamp", "type":"date", "validations": ""},
{"field" : "date_of_birth:timestamp", "type":"date", "validations": ""},
{"field" : "dob_month:string:nullable", "type":"select:01,02,03,04,05,06,07,08,09,10,11,12", "validations": ""},
{"field" : "dob_day:string:nullable", "type":"select:01,02,03,04,05,06,07,08,09,10,11,12,13,14,15,16,17,18,19,20,21,22,23,24,25,26,27,28,29,30", "validations": ""},
{"field" : "dob_year:string:default,1980", "type":"text", "validations": ""},
{"field" : "profile_activated_on:timestamp", "type":"date", "validations": ""},
{"field" : "activated_on:timestamp", "type":"date", "validations": ""},
{"field" : "published_on:timestamp", "type":"date", "validations": ""},
{"field" : "user_id:integer:unsigned:foreign:references,id:on,users:onDelete,cascade", "type":"select", "validations": ""}
]